younit/__init__.py
younit/__version__.py
younit/main.py
younit-0.1.0.dist-info/DESCRIPTION.rst
younit-0.1.0.dist-info/METADATA
younit-0.1.0.dist-info/RECORD
younit-0.1.0.dist-info/WHEEL
younit-0.1.0.dist-info/metadata.json
younit-0.1.0.dist-info/top_level.txt
