Metadata-Version: 2.0
Name: younit
Version: 0.1.0
Summary: a collection of helpers for the unittest module
Home-page: https://github.com/jeremyarr/younit
Author: Jeremy Arr
Author-email: jeremyarr@gmail.com
License: MIT
Keywords: asyncio,unittest,mock,testing
Platform: UNKNOWN
Classifier: Development Status :: 2 - Pre-Alpha
Classifier: License :: OSI Approved :: MIT License
Classifier: Intended Audience :: Developers
Classifier: Programming Language :: Python :: 3.6
